[
  {
    "task": "arithmetic",
    "sampler": "random",
    "steps": 2,
    "accuracy": 0.9566666666666667,
    "n_examples": 300,
    "n_forward": 10,
    "n_backward": 0,
    "wall_time_s": 0.1315378790000068,
    "extra": {},
    "kind": "pareto"
  },
  {
    "task": "arithmetic",
    "sampler": "confidence",
    "steps": 2,
    "accuracy": 0.96,
    "n_examples": 300,
    "n_forward": 10,
    "n_backward": 0,
    "wall_time_s": 0.11779344999968089,
    "extra": {},
    "kind": "pareto"
  },
  {
    "task": "arithmetic",
    "sampler": "margin",
    "steps": 2,
    "accuracy": 0.96,
    "n_examples": 300,
    "n_forward": 10,
    "n_backward": 0,
    "wall_time_s": 0.13046512600021742,
    "extra": {},
    "kind": "pareto"
  },
  {
    "task": "arithmetic",
    "sampler": "entropy",
    "steps": 2,
    "accuracy": 0.96,
    "n_examples": 300,
    "n_forward": 10,
    "n_backward": 0,
    "wall_time_s": 0.12269990799995867,
    "extra": {},
    "kind": "pareto"
  },
  {
    "task": "arithmetic",
    "sampler": "boe",
    "steps": 2,
    "accuracy": 0.96,
    "n_examples": 300,
    "n_forward": 20,
    "n_backward": 10,
    "wall_time_s": 0.49235054699965985,
    "extra": {},
    "kind": "pareto"
  },
  {
    "task": "arithmetic",
    "sampler": "random",
    "steps": 4,
    "accuracy": 0.9566666666666667,
    "n_examples": 300,
    "n_forward": 15,
    "n_backward": 0,
    "wall_time_s": 0.14423406700007035,
    "extra": {},
    "kind": "pareto"
  },
  {
    "task": "arithmetic",
    "sampler": "confidence",
    "steps": 4,
    "accuracy": 0.96,
    "n_examples": 300,
    "n_forward": 15,
    "n_backward": 0,
    "wall_time_s": 0.1414513309996437,
    "extra": {},
    "kind": "pareto"
  },
  {
    "task": "arithmetic",
    "sampler": "margin",
    "steps": 4,
    "accuracy": 0.96,
    "n_examples": 300,
    "n_forward": 15,
    "n_backward": 0,
    "wall_time_s": 0.135644898999999,
    "extra": {},
    "kind": "pareto"
  },
  {
    "task": "arithmetic",
    "sampler": "entropy",
    "steps": 4,
    "accuracy": 0.96,
    "n_examples": 300,
    "n_forward": 15,
    "n_backward": 0,
    "wall_time_s": 0.12796156699960193,
    "extra": {},
    "kind": "pareto"
  },
  {
    "task": "arithmetic",
    "sampler": "boe",
    "steps": 4,
    "accuracy": 0.96,
    "n_examples": 300,
    "n_forward": 30,
    "n_backward": 15,
    "wall_time_s": 0.5672625679999328,
    "extra": {},
    "kind": "pareto"
  },
  {
    "task": "arithmetic",
    "sampler": "random",
    "steps": 8,
    "accuracy": 0.9566666666666667,
    "n_examples": 300,
    "n_forward": 15,
    "n_backward": 0,
    "wall_time_s": 0.13559857500013095,
    "extra": {},
    "kind": "pareto"
  },
  {
    "task": "arithmetic",
    "sampler": "confidence",
    "steps": 8,
    "accuracy": 0.96,
    "n_examples": 300,
    "n_forward": 15,
    "n_backward": 0,
    "wall_time_s": 0.12511527299966474,
    "extra": {},
    "kind": "pareto"
  },
  {
    "task": "arithmetic",
    "sampler": "margin",
    "steps": 8,
    "accuracy": 0.96,
    "n_examples": 300,
    "n_forward": 15,
    "n_backward": 0,
    "wall_time_s": 0.13171629099997517,
    "extra": {},
    "kind": "pareto"
  },
  {
    "task": "arithmetic",
    "sampler": "entropy",
    "steps": 8,
    "accuracy": 0.96,
    "n_examples": 300,
    "n_forward": 15,
    "n_backward": 0,
    "wall_time_s": 0.13403620500002944,
    "extra": {},
    "kind": "pareto"
  },
  {
    "task": "arithmetic",
    "sampler": "boe",
    "steps": 8,
    "accuracy": 0.96,
    "n_examples": 300,
    "n_forward": 30,
    "n_backward": 15,
    "wall_time_s": 0.6159777259999828,
    "extra": {},
    "kind": "pareto"
  },
  {
    "task": "sudoku4",
    "sampler": "random",
    "steps": 2,
    "accuracy": 0.23333333333333334,
    "n_examples": 300,
    "n_forward": 10,
    "n_backward": 0,
    "wall_time_s": 0.13534456299976227,
    "extra": {},
    "kind": "pareto"
  },
  {
    "task": "sudoku4",
    "sampler": "confidence",
    "steps": 2,
    "accuracy": 0.24,
    "n_examples": 300,
    "n_forward": 10,
    "n_backward": 0,
    "wall_time_s": 0.1293718010001612,
    "extra": {},
    "kind": "pareto"
  },
  {
    "task": "sudoku4",
    "sampler": "margin",
    "steps": 2,
    "accuracy": 0.22,
    "n_examples": 300,
    "n_forward": 10,
    "n_backward": 0,
    "wall_time_s": 0.13095130900001095,
    "extra": {},
    "kind": "pareto"
  },
  {
    "task": "sudoku4",
    "sampler": "entropy",
    "steps": 2,
    "accuracy": 0.22333333333333333,
    "n_examples": 300,
    "n_forward": 10,
    "n_backward": 0,
    "wall_time_s": 0.11729406499989636,
    "extra": {},
    "kind": "pareto"
  },
  {
    "task": "sudoku4",
    "sampler": "boe",
    "steps": 2,
    "accuracy": 0.23,
    "n_examples": 300,
    "n_forward": 20,
    "n_backward": 10,
    "wall_time_s": 0.5436123479998969,
    "extra": {},
    "kind": "pareto"
  },
  {
    "task": "sudoku4",
    "sampler": "random",
    "steps": 4,
    "accuracy": 0.29333333333333333,
    "n_examples": 300,
    "n_forward": 20,
    "n_backward": 0,
    "wall_time_s": 0.2420700749999014,
    "extra": {},
    "kind": "pareto"
  },
  {
    "task": "sudoku4",
    "sampler": "confidence",
    "steps": 4,
    "accuracy": 0.30333333333333334,
    "n_examples": 300,
    "n_forward": 20,
    "n_backward": 0,
    "wall_time_s": 0.24898659800010137,
    "extra": {},
    "kind": "pareto"
  },
  {
    "task": "sudoku4",
    "sampler": "margin",
    "steps": 4,
    "accuracy": 0.31,
    "n_examples": 300,
    "n_forward": 20,
    "n_backward": 0,
    "wall_time_s": 0.23195924999981798,
    "extra": {},
    "kind": "pareto"
  },
  {
    "task": "sudoku4",
    "sampler": "entropy",
    "steps": 4,
    "accuracy": 0.29333333333333333,
    "n_examples": 300,
    "n_forward": 20,
    "n_backward": 0,
    "wall_time_s": 0.22586620099991706,
    "extra": {},
    "kind": "pareto"
  },
  {
    "task": "sudoku4",
    "sampler": "boe",
    "steps": 4,
    "accuracy": 0.38,
    "n_examples": 300,
    "n_forward": 40,
    "n_backward": 20,
    "wall_time_s": 1.162471733000075,
    "extra": {},
    "kind": "pareto"
  },
  {
    "task": "sudoku4",
    "sampler": "random",
    "steps": 8,
    "accuracy": 0.4,
    "n_examples": 300,
    "n_forward": 40,
    "n_backward": 0,
    "wall_time_s": 0.5415513819998523,
    "extra": {},
    "kind": "pareto"
  },
  {
    "task": "sudoku4",
    "sampler": "confidence",
    "steps": 8,
    "accuracy": 0.44333333333333336,
    "n_examples": 300,
    "n_forward": 40,
    "n_backward": 0,
    "wall_time_s": 0.5611426630002825,
    "extra": {},
    "kind": "pareto"
  },
  {
    "task": "sudoku4",
    "sampler": "margin",
    "steps": 8,
    "accuracy": 0.44333333333333336,
    "n_examples": 300,
    "n_forward": 40,
    "n_backward": 0,
    "wall_time_s": 0.5271044589999292,
    "extra": {},
    "kind": "pareto"
  },
  {
    "task": "sudoku4",
    "sampler": "entropy",
    "steps": 8,
    "accuracy": 0.44666666666666666,
    "n_examples": 300,
    "n_forward": 40,
    "n_backward": 0,
    "wall_time_s": 0.5658419110000068,
    "extra": {},
    "kind": "pareto"
  },
  {
    "task": "sudoku4",
    "sampler": "boe",
    "steps": 8,
    "accuracy": 0.46,
    "n_examples": 300,
    "n_forward": 80,
    "n_backward": 40,
    "wall_time_s": 2.191375470999901,
    "extra": {},
    "kind": "pareto"
  }
]